oxidizedvision/__init__.py
oxidizedvision/benchmark.py
oxidizedvision/cli.py
oxidizedvision/config.py
oxidizedvision/convert.py
oxidizedvision/validate.py
oxidizedvision-1.0.1.dist-info/licenses/LICENSE
tests/__init__.py
tests/test_convert.py
oxidizedvision-1.0.1.dist-info/METADATA
oxidizedvision-1.0.1.dist-info/WHEEL
oxidizedvision-1.0.1.dist-info/entry_points.txt
oxidizedvision-1.0.1.dist-info/top_level.txt
oxidizedvision-1.0.1.dist-info/RECORD
